{
  "tableData": [
    {
      "rank": "1",
      "archetype": "Abzan",
      "winrate": "64.29%",
      "num_drafts": "7"
    },
    {
      "rank": "2",
      "archetype": "Selesnya",
      "winrate": "62.50%",
      "num_drafts": "12"
    },
    {
      "rank": "3",
      "archetype": "Orzhov",
      "winrate": "60.00%",
      "num_drafts": "15"
    },
    {
      "rank": "4",
      "archetype": "Temur",
      "winrate": "60.00%",
      "num_drafts": "5"
    },
    {
      "rank": "5",
      "archetype": "Azorius",
      "winrate": "58.62%",
      "num_drafts": "15"
    },
    {
      "rank": "6",
      "archetype": "Rakdos",
      "winrate": "56.52%",
      "num_drafts": "12"
    },
    {
      "rank": "7",
      "archetype": "Naya",
      "winrate": "55.56%",
      "num_drafts": "9"
    },
    {
      "rank": "8",
      "archetype": "Dimir",
      "winrate": "54.05%",
      "num_drafts": "18"
    },
    {
      "rank": "9",
      "archetype": "Izzet",
      "winrate": "52.17%",
      "num_drafts": "12"
    },
    {
      "rank": "10",
      "archetype": "5c",
      "winrate": "50.00%",
      "num_drafts": "5"
    },
    {
      "rank": "11",
      "archetype": "Jund",
      "winrate": "50.00%",
      "num_drafts": "7"
    },
    {
      "rank": "12",
      "archetype": "Boros",
      "winrate": "48.00%",
      "num_drafts": "13"
    },
    {
      "rank": "13",
      "archetype": "Esper",
      "winrate": "47.06%",
      "num_drafts": "9"
    },
    {
      "rank": "14",
      "archetype": "Simic",
      "winrate": "42.86%",
      "num_drafts": "7"
    },
    {
      "rank": "15",
      "archetype": "Mardu",
      "winrate": "41.67%",
      "num_drafts": "7"
    },
    {
      "rank": "16",
      "archetype": "Gruul",
      "winrate": "38.24%",
      "num_drafts": "18"
    },
    {
      "rank": "17",
      "archetype": "Golgari",
      "winrate": "35.48%",
      "num_drafts": "16"
    }
  ]
}
