{
  "tableData": [
    {
      "rank": "1*",
      "name": "Tony",
      "win_percentage": "69.57%",
      "wins_losses": "16-7",
      "total_drafts": "12",
      "glicko": "1637 ± 99",
      "gxe": "62.67%",
      "last_set": "MB2",
      "last_date": "4-24-25"
    },
    {
      "rank": "2*",
      "name": "Collin",
      "win_percentage": "63.64%",
      "wins_losses": "14-8",
      "total_drafts": "11",
      "glicko": "1577 ± 93",
      "gxe": "57.19%",
      "last_set": "MB2",
      "last_date": "5-22-25"
    },
    {
      "rank": "3*",
      "name": "Eric",
      "win_percentage": "63.04%",
      "wins_losses": "29-17",
      "total_drafts": "22",
      "glicko": "1650 ± 73",
      "gxe": "63.86%",
      "last_set": "Chaos",
      "last_date": "5-17-25"
    },
    {
      "rank": "4",
      "name": "Andrew D",
      "win_percentage": "62.50%",
      "wins_losses": "10-6",
      "total_drafts": "7",
      "glicko": "1637 ± 100",
      "gxe": "62.61%",
      "last_set": "MB2",
      "last_date": "5-22-25"
    },
    {
      "rank": "5",
      "name": "Travis",
      "win_percentage": "62.50%",
      "wins_losses": "5-3",
      "total_drafts": "4",
      "glicko": "1464 ± 136",
      "gxe": "46.71%",
      "last_set": "Chaos",
      "last_date": "5-22-25"
    },
    {
      "rank": "6*",
      "name": "Noah",
      "win_percentage": "60.61%",
      "wins_losses": "20-13",
      "total_drafts": "16",
      "glicko": "1578 ± 80",
      "gxe": "57.36%",
      "last_set": "MB2",
      "last_date": "5-22-25"
    },
    {
      "rank": "7*",
      "name": "Walski",
      "win_percentage": "59.50%",
      "wins_losses": "22-15",
      "total_drafts": "19",
      "glicko": "1589 ± 76",
      "gxe": "58.42%",
      "last_set": "Chaos",
      "last_date": "5-22-25"
    },
    {
      "rank": "8*",
      "name": "Luis",
      "win_percentage": "59.09%",
      "wins_losses": "13-9",
      "total_drafts": "11",
      "glicko": "1577 ± 90",
      "gxe": "57.24%",
      "last_set": "Chaos",
      "last_date": "5-17-25"
    },
    {
      "rank": "9*",
      "name": "Adam",
      "win_percentage": "58.06%",
      "wins_losses": "18-13",
      "total_drafts": "15",
      "glicko": "1577 ± 80",
      "gxe": "57.22%",
      "last_set": "MB2",
      "last_date": "5-17-25"
    },
    {
      "rank": "10*",
      "name": "Chris A",
      "win_percentage": "57.50%",
      "wins_losses": "23-17",
      "total_drafts": "20",
      "glicko": "1595 ± 74",
      "gxe": "58.91%",
      "last_set": "Chaos",
      "last_date": "5-22-25"
    },
    {
      "rank": "11*",
      "name": "Alan",
      "win_percentage": "56.76%",
      "wins_losses": "21-16",
      "total_drafts": "18",
      "glicko": "1596 ± 75",
      "gxe": "59.04%",
      "last_set": "Chaos",
      "last_date": "5-22-25"
    },
    {
      "rank": "12",
      "name": "Aaron",
      "win_percentage": "56.25%",
      "wins_losses": "9-7",
      "total_drafts": "8",
      "glicko": "1497 ± 101",
      "gxe": "49.72%",
      "last_set": "Chaos",
      "last_date": "5-17-25"
    },
    {
      "rank": "13",
      "name": "David O",
      "win_percentage": "55.00%",
      "wins_losses": "11-9",
      "total_drafts": "10",
      "glicko": "1571 ± 93",
      "gxe": "56.63%",
      "last_set": "Chaos",
      "last_date": "5-17-25"
    },
    {
      "rank": "14",
      "name": "Kevin",
      "win_percentage": "50.00%",
      "wins_losses": "9-9",
      "total_drafts": "9",
      "glicko": "1470 ± 99",
      "gxe": "47.22%",
      "last_set": "Chaos",
      "last_date": "5-17-25"
    },
    {
      "rank": "15",
      "name": "Luke",
      "win_percentage": "50.00%",
      "wins_losses": "9-9",
      "total_drafts": "8",
      "glicko": "1507 ± 97",
      "gxe": "50.64%",
      "last_set": "Chaos",
      "last_date": "5-17-25"
    },
    {
      "rank": "16",
      "name": "Nick D",
      "win_percentage": "50.00%",
      "wins_losses": "6-6",
      "total_drafts": "6",
      "glicko": "1508 ± 118",
      "gxe": "50.77%",
      "last_set": "Chaos",
      "last_date": "5-17-25"
    },
    {
      "rank": "17",
      "name": "Matt Y",
      "win_percentage": "50.00%",
      "wins_losses": "6-6",
      "total_drafts": "6",
      "glicko": "1483 ± 125",
      "gxe": "48.44%",
      "last_set": "MH1",
      "last_date": "5-22-25"
    },
    {
      "rank": "18",
      "name": "John K",
      "win_percentage": "50.00%",
      "wins_losses": "5-5",
      "total_drafts": "5",
      "glicko": "1459 ± 130",
      "gxe": "46.22%",
      "last_set": "John Cube",
      "last_date": "5-8-25"
    },
    {
      "rank": "19",
      "name": "Oscar",
      "win_percentage": "50.00%",
      "wins_losses": "4-4",
      "total_drafts": "4",
      "glicko": "1527 ± 136",
      "gxe": "52.46%",
      "last_set": "Chaos",
      "last_date": "4-19-25"
    },
    {
      "rank": "20",
      "name": "Thana",
      "win_percentage": "41.67%",
      "wins_losses": "10-14",
      "total_drafts": "12",
      "glicko": "1476 ± 92",
      "gxe": "47.72%",
      "last_set": "MB2",
      "last_date": "5-22-25"
    },
    {
      "rank": "21",
      "name": "Stephen",
      "win_percentage": "33.33%",
      "wins_losses": "14-28",
      "total_drafts": "21",
      "glicko": "1384 ± 76",
      "gxe": "39.15%",
      "last_set": "Chaos",
      "last_date": "5-22-25"
    },
    {
      "rank": "22",
      "name": "Juwan",
      "win_percentage": "33.33%",
      "wins_losses": "3-6",
      "total_drafts": "5",
      "glicko": "1326 ± 138",
      "gxe": "34.49%",
      "last_set": "MB2",
      "last_date": "5-17-25"
    },
    {
      "rank": "23",
      "name": "Jacob",
      "win_percentage": "26.32%",
      "wins_losses": "5-14",
      "total_drafts": "10",
      "glicko": "1303 ± 98",
      "gxe": "32.20%",
      "last_set": "Chaos",
      "last_date": "5-22-25"
    },
    {
      "rank": "24",
      "name": "Marco",
      "win_percentage": "25.00%",
      "wins_losses": "6-18",
      "total_drafts": "12",
      "glicko": "1286 ± 94",
      "gxe": "30.80%",
      "last_set": "Chaos",
      "last_date": "5-22-25"
    },
    {
      "rank": "25",
      "name": "Jesse Luong",
      "win_percentage": "25.00%",
      "wins_losses": "2-6",
      "total_drafts": "4",
      "glicko": "1350 ± 139",
      "gxe": "36.50%",
      "last_set": "Chaos",
      "last_date": "5-17-25"
    },
    {
      "rank": "26",
      "name": "Simon",
      "win_percentage": "25.00%",
      "wins_losses": "2-6",
      "total_drafts": "4",
      "glicko": "1254 ± 143",
      "gxe": "28.76%",
      "last_set": "Chaos",
      "last_date": "5-22-25"
    },
    {
      "rank": "27",
      "name": "Zane",
      "win_percentage": "0.00%",
      "wins_losses": "0-8",
      "total_drafts": "4",
      "glicko": "1023 ± 163",
      "gxe": "14.96%",
      "last_set": "MB2",
      "last_date": "4-24-25"
    }
  ]
}
